{"title":"Combined feed","url":"https://ITCORD.github.io/mirakle/all.xml","elements":[{"title":"디캠프 12월 프리디데이에서 ‘알피’우승 (미라클 어헤드 ─ Think Big 뉴스종합 ─ Startup)","contents":"은행권청년창업재단 디캠프(상임이사 김영덕)는 이번 12 월 프리 디데이에서 알피(대표 김중희)가 우승했다고 19일 밝혔다. 17 일 서울대학교 의과대학 융합관 양윤선홀에서 개최된 이번 행사는 서울대학교 의과대..","link":"https://mirakle.mk.co.kr/view.php?sc=51800015&year=2022&no=1138484","retrieved":1671491466019,"image":"https://file.mk.co.kr/meet/neds/2022/12/image_readtop_2022_1138484_16714341025281887.jpg"},{"title":"핏펫, 반려동물 아플 때 꼭 필요한 ‘케어’ 서비스 신규 론칭 (미라클 어헤드 ─ Think Big 뉴스종합 ─ Startup)","contents":"건강한 반려생활을 선도하는 핏펫(대표 고정욱)이  기존의 ‘병원찾기’ 기능을 업그레이드 한 ‘케어’ 서비스를 새롭게 론칭 한다고 19일 밝혔다. 반려동물의 특성 상 같은 질환이라도 상태나 증상이 매우 다르기..","link":"https://mirakle.mk.co.kr/view.php?sc=51800015&year=2022&no=1138332","retrieved":1671491466021,"image":"https://file.mk.co.kr/meet/neds/2022/12/image_readtop_2022_1138332_16714331425281822.png"},{"title":"뤼튼테크놀로지스, K-디지털 그랜드 챔피언십에서 ‘최우수상’ 수상 (미라클 어헤드 ─ Think Big 뉴스종합 ─ Startup)","contents":"민관의 창업벤처 프로그램 집중지원을 통해 국내 최고의 디지털 청년기업 발굴과 육성을 위한 ‘2022 K-디지털 그랜드 챔피언십’에서 뤼튼테크놀로지스가 최우수상을 수상했다. 경기 스타트업캠퍼스에서 열린 ‘K-..","link":"https://mirakle.mk.co.kr/view.php?sc=51800015&year=2022&no=1137603","retrieved":1671491466022,"image":"https://file.mk.co.kr/meet/neds/2022/12/image_readtop_2022_1137603_16714251025281616.jpg"},{"title":"퓨처플레이, 2022년 결산 ‘퓨처플레이, 2022 혁신의 기록’ 공개 (미라클 어헤드 ─ Think Big 뉴스종합 ─ Startup)","contents":"퓨처플레이(각자대표 류중희, 권오형)가 2022년의 성과를 결산한 ‘퓨처플레이, 2022 혁신의 기록’을 19일 공개했다. 이번 수치는 2022년 12월 5일 기준이다. 먼저 퓨처플레이는 150억 원 규모의 프리IPO(상장 전 ..","link":"https://mirakle.mk.co.kr/view.php?sc=51800015&year=2022&no=1137304","retrieved":1671491466023,"image":"https://file.mk.co.kr/meet/neds/2022/12/image_readtop_2022_1137304_16714182615281496.jpg"},{"title":"와디즈, 올해 펀딩 시장을 이끈 영향력 있는 브랜드 ‘2022 와디즈 어워즈’ TOP 10 발표 (미라클 어헤드 ─ Think Big 뉴스종합 ─ Startup)","contents":"2022년 펀딩 시장에서 맹활약하며 주목받은 10팀의 베스트 메이커가 탄생했다. 라이프디자인 펀딩플랫폼 와디즈(대표 신혜성)는 올 한 해를 마무리하며, 와디즈를 통해 혁신적이고 새로운 서비스로 일상의 변화를 ..","link":"https://mirakle.mk.co.kr/view.php?sc=51800015&year=2022&no=1137266","retrieved":1671491466026,"image":"https://file.mk.co.kr/meet/neds/2022/12/image_readtop_2022_1137266_16714179625281480.jpg"},{"title":"아이와 부모가 모두 만족하는 차일드케어 서비스로의 성장, 디프런트도어즈 (미라클 어헤드 ─ Think Big 뉴스종합 ─ Startup)","contents":"“아이들을 위한, 아이들과 사는 방식을 고민합니다. 어린이를 위한 공간을 새로운 방식으로 만듭니다“ 블루포인트파트너스 입주 공간에서 만난 디프런트도어즈 김보경 대표의 말이다. 디프런트도어즈는 블루포인..","link":"https://mirakle.mk.co.kr/view.php?sc=51800015&year=2022&no=1137218","retrieved":1671491466029,"image":"https://file.mk.co.kr/meet/neds/2022/12/image_readtop_2022_1137218_16714249225281612.jpg"},{"title":"종합 리빙 플랫폼 어반베이스,\n\n리빙 복합문화공간 ‘어반베이스 동탄’ 개관 (미라클 어헤드 ─ Think Big 뉴스종합 ─ Startup)","contents":"가상 인테리어 플랫폼 ㈜어반베이스(대표 하진우)가 토탈 리빙 브랜드로 도약하기 위한 첫 여정을 시작했다. 어반베이스는 리빙 복합문화공간인 ‘어반베이스 동탄’의 개관식을 갖고 본격 운영에 들어갔다고 밝혔..","link":"https://mirakle.mk.co.kr/view.php?sc=51800015&year=2022&no=1137217","retrieved":1671491466030,"image":"https://file.mk.co.kr/meet/neds/2022/12/image_readtop_2022_1137217_16714173625281447.jpg"},{"title":"부동산 조각투자 ‘펀블’ 앱, 누적 다운로드 수 10만 돌파 (미라클 어헤드 ─ Think Big 뉴스종합 ─ Startup)","contents":"부동산 조각투자 플랫폼 서비스인 ‘펀블’ 앱이 출시 5개월만에 누적 다운로드 수 10만을 돌파했다. 펀블은 소수의  자산가들만이 가능하다고 여겨지던 고액의 상업용 부동산 투자를 STO(Security Token Offering)..","link":"https://mirakle.mk.co.kr/view.php?sc=51800015&year=2022&no=1136418","retrieved":1671491466039,"image":"https://file.mk.co.kr/meet/neds/2022/12/image_readtop_2022_1136418_16714108815281199.png"},{"title":"H2O X 리플레이스, 지방 소멸 위기 극복 위해 광주시와 협약 체결 (미라클 어헤드 ─ Think Big 뉴스종합 ─ Startup)","contents":"소멸 위기에 처한 국내 지방 도시에서 지역 특성을 살린 매력적인 공간을 만들어 온 H2O호스피탈리티 자회사 리플레이스(대표 도원우)가 광주법인 ‘광지주’를 설립하고 광주 전남 지역의 지방 소멸 위기 문제 해..","link":"https://mirakle.mk.co.kr/view.php?sc=51800015&year=2022&no=1136400","retrieved":1671491466045,"image":"https://file.mk.co.kr/meet/neds/2022/12/image_readtop_2022_1136400_16714106425281190.jpg"},{"title":"하우스앱, ‘패션 뷰티’ 카테고리 론칭…라이프스타일 커머스 도약 (미라클 어헤드 ─ Think Big 뉴스종합 ─ Startup)","contents":"국내 최대 숏폼 리뷰 커머스 플랫폼 ‘하우스앱(Houseapp)’을 운영하는 하우스미디어(대표이사 김성민)는 쇼핑 카테고리를 패션 뷰티로 확장하고 이를 기념한 연말 기획전을 진행한다고 19일 밝혔다. 하우스앱은 ..","link":"https://mirakle.mk.co.kr/view.php?sc=51800015&year=2022&no=1136383","retrieved":1671491466046,"image":"https://file.mk.co.kr/meet/neds/2022/12/image_readtop_2022_1136383_16714104625281183.jpg"},{"title":"노벨경제학상 임번스 교수 \"기본소득제 클 경우 일할 의욕 꺾어\" (미라클 어헤드 ─ Think Big 뉴스종합 ─ Global now)","contents":"기본소득이 클 경우 일할 인센티브가 줄어들 수 있습니다.  휘도 임번스 스탠포드대 교수는 2021년 노벨 경제학 수상자로 호명된 직후 스탠포드대 주최로 열린 온라인 기자간담회에서 이 같이 밝혔다. 임번스 교..","link":"https://mirakle.mk.co.kr/view.php?sc=51800013&year=2021&no=963369","retrieved":1671505749828,"image":"https://file.mk.co.kr/meet/neds/2021/10/image_readtop_2021_963369_16339813354812249.jpg"},{"title":"어메이즈VR, CJ포디플렉스 손잡고 \"글로벌 아티스트 VR 콘서트\" (미라클 어헤드 ─ Think Big 뉴스종합 ─ Global now)","contents":"VR 테크 스타트업 어메이즈VR(공동대표 이승준·어니스트 리)는 시네마 기술 기업 CJ 포디플렉스(대표 김종열)와 글로벌 톱 아티스트을 대상으로 한 VR 콘서트 제작·유통을 파트너십을 맺었다고 9일(현지시각) 밝..","link":"https://mirakle.mk.co.kr/view.php?sc=51800013&year=2021&no=875230","retrieved":1671505749832,"image":"https://file.mk.co.kr/meet/neds/2021/09/image_readtop_2021_875230_16312493554780806.jpg"},{"title":"성차별 방치한 블리자드 CEO 사임 (미라클 어헤드 ─ Think Big 뉴스종합 ─ Global now)","contents":"세계 최대 게임업체로 꼽히는 액티비전 블리자드의 앨런 브랙 최고경영자(CEO·사진)가 사내 성차별을 묵인하고 성희롱 논란을 해결하지 못해 끝내 사표를 제출했다. 3일(현지시간) 액티비전 블리자드는 성명서를 ..","link":"https://mirakle.mk.co.kr/view.php?sc=51800013&year=2021&no=755360","retrieved":1671505749845,"image":"https://file.mk.co.kr/meet/neds/2021/08/image_readtop_2021_755360_16280727324740669.jpg"},{"title":"한·중·일은 정보량, 서양인은 심플…좋은 앱 판별기준 문화따라 달라요 (미라클 어헤드 ─ Think Big 뉴스종합 ─ Global now)","contents":"같은 디자인이더라도 사용자마다 받아들이는 경험이 다르기 때문에 다양한 문화를 어떻게 포용할 수 있을지 발견하는 것이 사용자경험(UX)의 핵심입니다.  구글 내에는 전 세계 사용자 43억명이 어떻게 하면 보..","link":"https://mirakle.mk.co.kr/view.php?sc=51800013&year=2021&no=729526","retrieved":1671505749857,"image":"https://file.mk.co.kr/meet/neds/2021/07/image_readtop_2021_729526_16274672514732687.jpg"},{"title":"엑셀·구글 캘린더 묶었다…SW 한꺼번에 쓰는 `스윗` (미라클 어헤드 ─ Think Big 뉴스종합 ─ Global now)","contents":"◆ MK 인더스트리 리뷰 ◆    회사 업무를 보기 위해 메신저 프로그램을 열었다가, 이메일을 실행시켰다가, 워드프로세서를 열었다가, 캘린더를 열었다가, 영상회의까지 하다 보니 대체 내가 어떤 일을 하고 있었던 ..","link":"https://mirakle.mk.co.kr/view.php?sc=51800013&year=2021&no=197548","retrieved":1671505749864,"image":"https://file.mk.co.kr/meet/2021/03/image_listmain_2021_197548_1614668466.jpg"},{"title":"[실리콘밸리 리포트] \"자율차 디자인 걸음마 단계…가능성 무궁무진\" (미라클 어헤드 ─ Think Big 뉴스종합 ─ Global now)","contents":"새로운 자율주행차 형태의 등장은 시작 단계일 뿐이에요. 도전의 가능성이 많죠. 예를 들면 저는 개인적으로 미래의 자율주행차 디자인은 운전자 중심이 아니라 승객이 중심이 되는 형태가 될 수 있을 거라고 봐요...","link":"https://mirakle.mk.co.kr/view.php?sc=51800013&year=2021&no=179137","retrieved":1671505749864,"image":"https://file.mk.co.kr/meet/neds/2021/02/image_readtop_2021_179137_16141227364550324.jpg"},{"title":"인싸들의 은밀한 랜선파티…음성 `클럽하우스` (미라클 어헤드 ─ Think Big 뉴스종합 ─ Global now)","contents":"한국시간 5일오후 2시 30분. 마크 저커버그 페이스북 최고경영자(CEO)가 `클럽하우스`에 등장했다. 그는 약 20분간 최근 잘 팔리는 자사의 가상현실(VR) 디바이스 `오큘러스 퀘스트2` 이야기와 VR 시장의 미래가 ..","link":"https://mirakle.mk.co.kr/view.php?sc=51800013&year=2021&no=123830","retrieved":1671505749864,"image":"https://file.mk.co.kr/meet/2021/02/image_listmain_2021_123830_1612771214.jpg"},{"title":"지난해 314개 스타트업 투자한 엔젤 (미라클 어헤드 ─ Think Big 뉴스종합 ─ Global now)","contents":"실리콘밸리에 기반한 엔젤투자자 연합인 케이레츠포럼이 지난해 코로나19 사태에도 불구하고 전년대비 16% 증가한 초기 투자 건수를 기록했다고 5일 밝혔다. 건수로 치면 모두 314건이나 되는 스타트업에 투자했다. ..","link":"https://mirakle.mk.co.kr/view.php?sc=51800013&year=2021&no=123643","retrieved":1671505749865,"image":"https://file.mk.co.kr/meet/neds/2021/02/image_readtop_2021_123643_16125093914532726.jpg"},{"title":"제프 베이조스, 아마존 CEO서 물러난다…깜짝 발표 (미라클 어헤드 ─ Think Big 뉴스종합 ─ Global now)","contents":"아마존 창업자인 제프 베이조스 CEO가 올해 상반기를 끝으로 CEO직에서 물러나겠다고 2일(현지시간) 밝혔다.아마존은 지난해 4분기 실적를 이날 공개하며 이 같은 계획을 깜짝 발표했다. 아마존은 오는 3분기부터 ..","link":"https://mirakle.mk.co.kr/view.php?sc=51800013&year=2021&no=111219","retrieved":1671505749865},{"title":"美선 굴삭기도 안사고 `구독`…일반기업보다 성장 6배 빨랐다 (미라클 어헤드 ─ Think Big 뉴스종합 ─ Global now)","contents":"◆ MK 인더스트리 리뷰 ◆  `코로나19 이후 ○○○○를 갖고 있는 기업들은 일반 기업에 비해 6배 정도 높은 매출 성장률을 기록했다.` 코로나19 이후 더욱 주목받고 있는 비즈니스 모델이 있다. 소상공인들은 물론 ..","link":"https://mirakle.mk.co.kr/view.php?sc=51800013&year=2021&no=56771","retrieved":1671505749865,"image":"https://file.mk.co.kr/meet/2021/01/image_listmain_2021_56771_1610964225.jpg"},{"title":"아프지마, 병원 입지분석 및 경쟁력 강화 컨설팅 서비스 출시 (미라클 어헤드 ─ Think Big 뉴스종합 ─ Startup)","contents":"비급여 진료항목 정보 조회 플랫폼 ‘아프지마’를 서비스하고 있는 아프지마(대표 김대이)가 전국 병의원별 입지분석 및 경쟁력 강화 컨설팅 서비스를 시작했다고 20일 밝혔다. 건강보험심사평가원에 의하면 2021..","link":"https://mirakle.mk.co.kr/view.php?sc=51800015&year=2022&no=1140485","retrieved":1671505821353,"image":"https://file.mk.co.kr/meet/neds/2022/12/image_readtop_2022_1140485_16715028025282808.png"},{"title":"AI 기반 외국어학습 전문 스타트업 에듀템\n\n중기부 ‘팁스’(TIPS) 선정 (미라클 어헤드 ─ Think Big 뉴스종합 ─ Startup)","contents":"AI 기반 외국어학습 전문 스타트업 ‘에듀템’(공동대표 신정훈 김진숙)이 중소벤처기업부 민간투자형 기술창업 투자 프로그램 팁스(TIPS)에 최종 선정됐다고 20일 밝혔다. 팁스는 중기부와 민간 투자사가 함께 시..","link":"https://mirakle.mk.co.kr/view.php?sc=51800015&year=2022&no=1140002","retrieved":1671505821358,"image":"https://file.mk.co.kr/meet/neds/2022/12/image_readtop_2022_1140002_16714988425282629.jpg"},{"title":"베스핀글로벌 日 합작법인 ‘지젠(G-gen)’, 설립 1년 만에 고객사 100곳 돌파 (미라클 어헤드 ─ Think Big 뉴스종합 ─ Startup)","contents":"클라우드 딜리버리 플랫폼 기업 베스핀글로벌(대표 이한주)과 일본의 클라우드 인티그레이터(Cloud Integrator) 기업 서버웍스(대표 오오이시 료)가 함께 설립한 합작 법인 ‘지젠(G-gen)’이 사업 추진 약 1년 만..","link":"https://mirakle.mk.co.kr/view.php?sc=51800015&year=2022&no=1139977","retrieved":1671505821359,"image":"https://file.mk.co.kr/meet/neds/2022/12/image_readtop_2022_1139977_16714986025282623.jpg"},{"title":"본투글로벌, “글로벌 비즈니스 기회 발굴, 10년 안에 글로벌 유니콘 기업 100개 키울 것” (미라클 어헤드 ─ Think Big 뉴스종합 ─ Startup)","contents":"“실리콘밸리처럼 많은 경륜과 혜안을 얻을 수 있는 글로벌 전문가 네트워크가 필요.”(센드버드 김동신 대표) “해외투자자들이나 글로벌 기업들이 신뢰할 수 있는 ‘크레디트 마크’로 역할해야”(쿼드벤처스 김..","link":"https://mirakle.mk.co.kr/view.php?sc=51800015&year=2022&no=1139959","retrieved":1671505821385,"image":"https://file.mk.co.kr/meet/neds/2022/12/image_readtop_2022_1139959_16715029225282815.jpg"},{"title":"플랫타익스체인지 ‘24365고객응대 시스템’ 구축,\n\n24시간 연중무휴, 실시간 전국 커버 응대 역량 선보일 것 (미라클 어헤드 ─ Think Big 뉴스종합 ─ Startup)","contents":"리버스 전문 가상자산 거래소 플랫타익스체인지(FlataExchange)는 투자자 보호와 실시간 응대 역량 강화를 위해 서울뿐만 아니라 대구 지역에도 콜센터를 여는 등 자체 고객 응대서비스 시스템 ‘24365체제’를 운..","link":"https://mirakle.mk.co.kr/view.php?sc=51800015&year=2022&no=1139951","retrieved":1671505821386,"image":"https://file.mk.co.kr/meet/neds/2022/12/image_readtop_2022_1139951_16714982425282608.jpg"},{"title":"마크비전, ‘IP 비즈니스 인프라 SaaS 기업’ 비전 선포 (미라클 어헤드 ─ Think Big 뉴스종합 ─ Startup)","contents":"인공지능 기업 마크비전이 ‘IP 비즈니스 인프라 SaaS 기업’을 새 비전으로 선포하고 단계별 경영전략 및 운영 방향성에 대해 발표했다. 마크비전은 그동안 IP 운영을 위한 통합적인 업무 환경을 제공하기 위해 진..","link":"https://mirakle.mk.co.kr/view.php?sc=51800015&year=2022&no=1139840","retrieved":1671505821386,"image":"https://file.mk.co.kr/meet/neds/2022/12/image_readtop_2022_1139840_16714973425282569.jpg"},{"title":"푸드 버티컬 플랫폼 윙잇, 2022 푸드 쇼핑 트렌드 키워드 ‘H.M.R’ 발표 (미라클 어헤드 ─ Think Big 뉴스종합 ─ Startup)","contents":"푸드 버티컬 커머스 스타트업 윙잇(대표 임승진)이 2022년을 정리하는 푸드 쇼핑 트렌드 키워드를 ‘H.M.R’로 선정했다고 20일 밝혔다. 윙잇은 올해 1월부터 11월까지의 사용자 실시간 검색어와 구매 데이터를 분..","link":"https://mirakle.mk.co.kr/view.php?sc=51800015&year=2022&no=1139808","retrieved":1671505821386,"image":"https://file.mk.co.kr/meet/neds/2022/12/image_readtop_2022_1139808_16714969215282556.jpg"},{"title":"메타버스 플랫폼 스페이셜, 유니티 기반 크리에이터 툴키트 공개… 몰입감 있는 ‘웹3’시대 견인한다 (미라클 어헤드 ─ Think Big 뉴스종합 ─ Startup)","contents":"메타버스 플랫폼 스페이셜(공동대표 이진하, 아난드 아가라왈라)이 20일 게임엔진 유니티 기반의 새로운 크리에이터 툴키트를 공개했다. 수준 높은 그래픽과 상호작용 경험을 쉽게 만들어 웹, 모바일, VR에서 실행..","link":"https://mirakle.mk.co.kr/view.php?sc=51800015&year=2022&no=1139800","retrieved":1671505821386,"image":"https://file.mk.co.kr/meet/neds/2022/12/image_readtop_2022_1139800_16714967415282554.png"},{"title":"마플코퍼레이션, CCO로 이효진 전 플러스엑스 대표 영입 (미라클 어헤드 ─ Think Big 뉴스종합 ─ Startup)","contents":"마플코퍼레이션이 크리에이터 브랜딩 강화를 위해 크리에이티브 전문가 이효진 전 플러스엑스 공동대표를 최고크리에이티브책임자(CCO)로 영입했다. 이효진 CCO는 2014년부터 브랜드 경험(BX) 디자이너로 활동해온 ..","link":"https://mirakle.mk.co.kr/view.php?sc=51800015&year=2022&no=1139714","retrieved":1671505821387,"image":"https://file.mk.co.kr/meet/neds/2022/12/image_readtop_2022_1139714_16714962025282545.jpg"},{"title":"콜로세움, 명절 선물을 위한 빠른 배송 서비스 구축 (미라클 어헤드 ─ Think Big 뉴스종합 ─ Startup)","contents":"콜로세움이 다가오는 23년 설날 연휴를 대비하고 명절 및 연말연시와 같이 특정 기간에만 물동량이 집중되는 시즌에 물량을 안정적으로 소화할 수 있는 ‘오늘배송’ 서비스를 시작한다고 20일 밝혔다. 이번 ‘오늘..","link":"https://mirakle.mk.co.kr/view.php?sc=51800015&year=2022&no=1139705","retrieved":1671505821390,"image":"https://file.mk.co.kr/meet/neds/2022/12/image_readtop_2022_1139705_16714960825282540.png"},{"title":"아프지마, 병원 입지분석 및 경쟁력 강화 컨설팅 서비스 출시 (미라클 어헤드 ─ Think Big 뉴스종합 ─ Startup)","contents":"비급여 진료항목 정보 조회 플랫폼 ‘아프지마’를 서비스하고 있는 아프지마(대표 김대이)가 전국 병의원별 입지분석 및 경쟁력 강화 컨설팅 서비스를 시작했다고 20일 밝혔다. 건강보험심사평가원에 의하면 2021..","link":"https://mirakle.mk.co.kr/view.php?sc=51800015&year=2022&no=1140485","retrieved":1671505821353,"image":"https://file.mk.co.kr/meet/neds/2022/12/image_readtop_2022_1140485_16715028025282808.png"},{"title":"AI 기반 외국어학습 전문 스타트업 에듀템\n\n중기부 ‘팁스’(TIPS) 선정 (미라클 어헤드 ─ Think Big 뉴스종합 ─ Startup)","contents":"AI 기반 외국어학습 전문 스타트업 ‘에듀템’(공동대표 신정훈 김진숙)이 중소벤처기업부 민간투자형 기술창업 투자 프로그램 팁스(TIPS)에 최종 선정됐다고 20일 밝혔다. 팁스는 중기부와 민간 투자사가 함께 시..","link":"https://mirakle.mk.co.kr/view.php?sc=51800015&year=2022&no=1140002","retrieved":1671505821358,"image":"https://file.mk.co.kr/meet/neds/2022/12/image_readtop_2022_1140002_16714988425282629.jpg"},{"title":"베스핀글로벌 日 합작법인 ‘지젠(G-gen)’, 설립 1년 만에 고객사 100곳 돌파 (미라클 어헤드 ─ Think Big 뉴스종합 ─ Startup)","contents":"클라우드 딜리버리 플랫폼 기업 베스핀글로벌(대표 이한주)과 일본의 클라우드 인티그레이터(Cloud Integrator) 기업 서버웍스(대표 오오이시 료)가 함께 설립한 합작 법인 ‘지젠(G-gen)’이 사업 추진 약 1년 만..","link":"https://mirakle.mk.co.kr/view.php?sc=51800015&year=2022&no=1139977","retrieved":1671505821359,"image":"https://file.mk.co.kr/meet/neds/2022/12/image_readtop_2022_1139977_16714986025282623.jpg"},{"title":"본투글로벌, “글로벌 비즈니스 기회 발굴, 10년 안에 글로벌 유니콘 기업 100개 키울 것” (미라클 어헤드 ─ Think Big 뉴스종합 ─ Startup)","contents":"“실리콘밸리처럼 많은 경륜과 혜안을 얻을 수 있는 글로벌 전문가 네트워크가 필요.”(센드버드 김동신 대표) “해외투자자들이나 글로벌 기업들이 신뢰할 수 있는 ‘크레디트 마크’로 역할해야”(쿼드벤처스 김..","link":"https://mirakle.mk.co.kr/view.php?sc=51800015&year=2022&no=1139959","retrieved":1671505821385,"image":"https://file.mk.co.kr/meet/neds/2022/12/image_readtop_2022_1139959_16715029225282815.jpg"},{"title":"플랫타익스체인지 ‘24365고객응대 시스템’ 구축,\n\n24시간 연중무휴, 실시간 전국 커버 응대 역량 선보일 것 (미라클 어헤드 ─ Think Big 뉴스종합 ─ Startup)","contents":"리버스 전문 가상자산 거래소 플랫타익스체인지(FlataExchange)는 투자자 보호와 실시간 응대 역량 강화를 위해 서울뿐만 아니라 대구 지역에도 콜센터를 여는 등 자체 고객 응대서비스 시스템 ‘24365체제’를 운..","link":"https://mirakle.mk.co.kr/view.php?sc=51800015&year=2022&no=1139951","retrieved":1671505821386,"image":"https://file.mk.co.kr/meet/neds/2022/12/image_readtop_2022_1139951_16714982425282608.jpg"},{"title":"마크비전, ‘IP 비즈니스 인프라 SaaS 기업’ 비전 선포 (미라클 어헤드 ─ Think Big 뉴스종합 ─ Startup)","contents":"인공지능 기업 마크비전이 ‘IP 비즈니스 인프라 SaaS 기업’을 새 비전으로 선포하고 단계별 경영전략 및 운영 방향성에 대해 발표했다. 마크비전은 그동안 IP 운영을 위한 통합적인 업무 환경을 제공하기 위해 진..","link":"https://mirakle.mk.co.kr/view.php?sc=51800015&year=2022&no=1139840","retrieved":1671505821386,"image":"https://file.mk.co.kr/meet/neds/2022/12/image_readtop_2022_1139840_16714973425282569.jpg"},{"title":"푸드 버티컬 플랫폼 윙잇, 2022 푸드 쇼핑 트렌드 키워드 ‘H.M.R’ 발표 (미라클 어헤드 ─ Think Big 뉴스종합 ─ Startup)","contents":"푸드 버티컬 커머스 스타트업 윙잇(대표 임승진)이 2022년을 정리하는 푸드 쇼핑 트렌드 키워드를 ‘H.M.R’로 선정했다고 20일 밝혔다. 윙잇은 올해 1월부터 11월까지의 사용자 실시간 검색어와 구매 데이터를 분..","link":"https://mirakle.mk.co.kr/view.php?sc=51800015&year=2022&no=1139808","retrieved":1671505821386,"image":"https://file.mk.co.kr/meet/neds/2022/12/image_readtop_2022_1139808_16714969215282556.jpg"},{"title":"메타버스 플랫폼 스페이셜, 유니티 기반 크리에이터 툴키트 공개… 몰입감 있는 ‘웹3’시대 견인한다 (미라클 어헤드 ─ Think Big 뉴스종합 ─ Startup)","contents":"메타버스 플랫폼 스페이셜(공동대표 이진하, 아난드 아가라왈라)이 20일 게임엔진 유니티 기반의 새로운 크리에이터 툴키트를 공개했다. 수준 높은 그래픽과 상호작용 경험을 쉽게 만들어 웹, 모바일, VR에서 실행..","link":"https://mirakle.mk.co.kr/view.php?sc=51800015&year=2022&no=1139800","retrieved":1671505821386,"image":"https://file.mk.co.kr/meet/neds/2022/12/image_readtop_2022_1139800_16714967415282554.png"},{"title":"마플코퍼레이션, CCO로 이효진 전 플러스엑스 대표 영입 (미라클 어헤드 ─ Think Big 뉴스종합 ─ Startup)","contents":"마플코퍼레이션이 크리에이터 브랜딩 강화를 위해 크리에이티브 전문가 이효진 전 플러스엑스 공동대표를 최고크리에이티브책임자(CCO)로 영입했다. 이효진 CCO는 2014년부터 브랜드 경험(BX) 디자이너로 활동해온 ..","link":"https://mirakle.mk.co.kr/view.php?sc=51800015&year=2022&no=1139714","retrieved":1671505821387,"image":"https://file.mk.co.kr/meet/neds/2022/12/image_readtop_2022_1139714_16714962025282545.jpg"},{"title":"콜로세움, 명절 선물을 위한 빠른 배송 서비스 구축 (미라클 어헤드 ─ Think Big 뉴스종합 ─ Startup)","contents":"콜로세움이 다가오는 23년 설날 연휴를 대비하고 명절 및 연말연시와 같이 특정 기간에만 물동량이 집중되는 시즌에 물량을 안정적으로 소화할 수 있는 ‘오늘배송’ 서비스를 시작한다고 20일 밝혔다. 이번 ‘오늘..","link":"https://mirakle.mk.co.kr/view.php?sc=51800015&year=2022&no=1139705","retrieved":1671505821390,"image":"https://file.mk.co.kr/meet/neds/2022/12/image_readtop_2022_1139705_16714960825282540.png"},{"title":"에듀테크 앱 어디가 잘 되나 (미라클 어헤드 ─ Think Big 뉴스종합 ─ Insights)","contents":"정보기술(IT)이 결합된 교육 ‘에듀테크(edutech)’는 2020년 국내 코로나 확진 발생 이후 급속도로 활성화됐다. 감염병 확산 우려로 비대면 교육이 불가피해졌기 때문이다. 에듀테크는 단순한 온라인 교육을 뛰어넘..","link":"https://mirakle.mk.co.kr/view.php?sc=51800016&year=2022&no=1116714","retrieved":1671513040763,"image":"https://file.mk.co.kr/meet/neds/2022/12/image_readtop_2022_1116714_16708221625272699.png"},{"title":"[유진평의 K스타트업 진(단)평(가)] 투자 빙하기...스타트업 엑싯(Exit) 지분매각 IPO 잘하려면 (미라클 어헤드 ─ Think Big 뉴스종합 ─ Insights)","contents":"경기 위축으로 스타트업 시장도 빙하기를 맞았네요. 그래서 씁쓸한 얘기지만, 지분 일부 또는 전부 매각 방식의 엑싯(exit)을 모색하는 창업자들이 많아지고 있다고 합니다. 거래소나 코스닥 시장에 상장하는 IPO(기..","link":"https://mirakle.mk.co.kr/view.php?sc=51800016&year=2022&no=1089153","retrieved":1671513040771,"image":"https://file.mk.co.kr/meet/neds/2022/12/image_readtop_2022_1089153_16699586425260587.jpg"},{"title":"루나 FTX 위믹스 사태까지…휘청대는 가상자산, 앱 사용자 현황은? (미라클 어헤드 ─ Think Big 뉴스종합 ─ Insights)","contents":"가상자산 약세장을 이르는 ‘크립토 윈터’가 지속되는 모양새다. 세계 각국의 금리 인상 기조에 따라 경기 침체 분위기가 이어지고 있는 탓이다. 지난 5월 ‘루나 사태’가 발생한 데 이어 반년도 채 지나지 않아 ..","link":"https://mirakle.mk.co.kr/view.php?sc=51800016&year=2022&no=1071181","retrieved":1671513040774,"image":"https://file.mk.co.kr/meet/neds/2022/11/image_readtop_2022_1071181_16696167025254398.png"},{"title":"‘온라인 쇼핑’ 업계의 성장…그 중심에는 ‘이것’이 있다 (미라클 어헤드 ─ Think Big 뉴스종합 ─ Insights)","contents":"온라인 쇼핑 시장 규모가 지속적으로 커지고 있다. 통계청이 발표한 ‘22년 9월 온라인 쇼핑 동향’에 따르면 지난 9월 기준 온라인 쇼핑 거래액은 총 17조 4,553억 원으로 지난해 동월 대비 약 11.8% 증가했다. 그 ..","link":"https://mirakle.mk.co.kr/view.php?sc=51800016&year=2022&no=1046152","retrieved":1671513040777,"image":"https://file.mk.co.kr/meet/neds/2022/11/image_readtop_2022_1046152_16690213825245607.png"},{"title":"‘카톡 오류’ 이전과 이후 변화는? (미라클 어헤드 ─ Think Big 뉴스종합 ─ Insights)","contents":"‘국민 앱’으로 불려도 손색없을 카카오톡이 지난 15일 ‘먹통’ 오류로 홍역을 치렀다. 2010년 출시된 이후 최장기간 이어진 서비스 오류 사태다. 나라 전체가 혼란에 빠질만한 것이 카카오톡뿐만 아니라 카카오T..","link":"https://mirakle.mk.co.kr/view.php?sc=51800016&year=2022&no=965268","retrieved":1671513040781,"image":"https://file.mk.co.kr/meet/neds/2022/10/image_readtop_2022_965268_16671769095215200.jpg"},{"title":"‘캠핑업계’ 엔데믹 이겨내고 가을 성수기 맞이할까 (미라클 어헤드 ─ Think Big 뉴스종합 ─ Insights)","contents":"#2010년부터 캠핑을 즐겨 온 30대 A 씨는 지난해 캠핑사이트를 예약하는 데 무척이나 애를 먹었다. 특히 벚꽃 시즌이나 단풍철에는 소위 말하는 ‘광클’로도 역부족일 만큼 원하는 장소나 자리를 예약하지 못 하는 ..","link":"https://mirakle.mk.co.kr/view.php?sc=51800016&year=2022&no=939457","retrieved":1671513040784,"image":"https://file.mk.co.kr/meet/neds/2022/10/image_readtop_2022_939457_16665712825207063.jpg"},{"title":"[유진평의 K스타트업 진(단)평(가)]스타트업 글로벌 진출 열쇠는 테크매칭 : 테크매칭 성사 실마리는  ‘리버스 피칭’ (미라클 어헤드 ─ Think Big 뉴스종합 ─ Insights)","contents":"‘글로벌은 이웃, 큰 시장에서 StartUp’ 혁신 기술 기업 해외진출을 지원하는 본투글로벌센터에서 바라 본 스타트업 생태계와 트렌드, 기술매칭 현황 등을 유진평 본투글로벌센터 미디어 전문위원이 소개합니다..","link":"https://mirakle.mk.co.kr/view.php?sc=51800016&year=2022&no=933517","retrieved":1671513040791,"image":"https://file.mk.co.kr/meet/neds/2022/10/image_readtop_2022_933517_16664238495204578.jpg"},{"title":"온라인 쇼핑 ‘훨훨’ 나는데…홈쇼핑 업계, 올 들어 고전 지속 (미라클 어헤드 ─ Think Big 뉴스종합 ─ Insights)","contents":"온라인 쇼핑 시대다. 통계청이 발표한 ‘2022년 8월 온라인쇼핑동향’에 따르면 지난 8월 기준 거래액은 총 17조 7,181억 원으로 전년 동월 대비 16%(2조 4,425억 원) 증가했다. 이 중 모바일쇼핑 거래액은 전체의 ..","link":"https://mirakle.mk.co.kr/view.php?sc=51800016&year=2022&no=915857","retrieved":1671513040817,"image":"https://file.mk.co.kr/meet/neds/2022/10/image_readtop_2022_915857_16659726035198866.jpg"},{"title":"‘백화점 진출’ 중고 시장…역할 컸던 중고 거래 플랫폼 살펴보니 (미라클 어헤드 ─ Think Big 뉴스종합 ─ Insights)","contents":"대기업 유통사가 중고 시장에 발을 담갔다. 2030세대를 중심으로 중고 거래가 활성화된 흐름에 올라탄 것이다. 현대백화점은 신촌점 4층 전체를 중고품 전문관인 ‘세컨드 부티크’로 탈바꿈시켰다. 신세계백화점도..","link":"https://mirakle.mk.co.kr/view.php?sc=51800016&year=2022&no=848589","retrieved":1671513040828,"image":"https://file.mk.co.kr/meet/neds/2022/09/image_readtop_2022_848589_16641696595178143.jpg"},{"title":"경기 침체에 불안한 증시…증권사 MTS 앱 현황은? (미라클 어헤드 ─ Think Big 뉴스종합 ─ Insights)","contents":"주식 시장이 대중화된 데는 스마트폰의 발달이 큰 영향을 미쳤다. MTS(Moblie Trading System) 도입으로 주식 거래 편의성이 높아짐에 따라 개인 투자자들이 대거 유입된 것이다. 지난해까지 열풍을 일으켰던 주식 ..","link":"https://mirakle.mk.co.kr/view.php?sc=51800016&year=2022&no=826353","retrieved":1671513040836,"image":"https://file.mk.co.kr/meet/neds/2022/09/image_readtop_2022_826353_16635795995170875.jpg"}]}