{"title":"미라클 어헤드 ─ Think Big 뉴스종합 ─ 전체","url":"https://mirakle.mk.co.kr/list.php?sc=51800012","favicon":"https://mirakle.mk.co.kr/favicon.ico","elements":[{"title":"엘리스, ‘제8기 혁신아이콘’ 선정…유니콘 기업으로 성장 가능성 확인","contents":"37대 1의 경쟁률과 3차에 걸친 치열한 경합 끝 최종 선발 플랫폼 활용해 교육과 프로젝트 실시하며 기업의 실질적..","link":"https://mirakle.mk.co.kr/view.php?sc=51800012&year=2022&no=1028013","retrieved":1668645667554,"image":"https://file.mk.co.kr/meet/neds/2022/11/image_readtop_2022_1028013_16686438615239589.jpg"},{"title":"리모델링 비용 부담 낮추는 가심비 패키지\n\n아파트멘터리, ‘파이브 스탠다드’ 출시","contents":"금리 및 자재비 인상으로 높아진 리모델링 비용 부담 덜어주는 가심비 패키지 상품 스탠다드 급의 자재와 대중적..","link":"https://mirakle.mk.co.kr/view.php?sc=51800012&year=2022&no=1027961","retrieved":1668645667585,"image":"https://file.mk.co.kr/meet/neds/2022/11/image_readtop_2022_1027961_16686435025239576.jpg"},{"title":"소부장 아기유니콘 FCMT, 2022 대한민국 발명특허대전 특허청장상 수상","contents":"MEA의 핵심 소재인 전극 설계?제조 기술력에 대한 IP 검증  수소 연료전지?수전해 ..","link":"https://mirakle.mk.co.kr/view.php?sc=51800012&year=2022&no=1027901","retrieved":1668645667591,"image":"https://file.mk.co.kr/meet/neds/2022/11/image_readtop_2022_1027901_16686433215239573.jpg"},{"title":"윌로그, 정보보호 및 환경경영시스템 국제표준 인증(ISO)\n\n3종 동시 획득","contents":"정보보안경영시스템 ISO27001, 클라우드정보보안지침 ISO27017, 환경경영시스템 ISO14001 3가지 국제표준 인증(IS..","link":"https://mirakle.mk.co.kr/view.php?sc=51800012&year=2022&no=1027873","retrieved":1668645667593,"image":"https://file.mk.co.kr/meet/neds/2022/11/image_readtop_2022_1027873_16686431415239570.jpg"},{"title":"넛지헬스케어㈜, 강남역 부근 신사옥 ‘넛지 캠퍼스’ 오픈","contents":"디지털 헬스케어 스타트업 넛지헬스케어㈜가 기업 경쟁력 강화를 위해 신사옥 ‘넛지 캠퍼스(NUDGE CAMPUS)’를 오픈했다. 신사옥 넛지 캠퍼스는 우수 인재 유치를 격려하고 임직원의 효율적인 근무 환경을 조성하..","link":"https://mirakle.mk.co.kr/view.php?sc=51800012&year=2022&no=1027831","retrieved":1668645667595,"image":"https://file.mk.co.kr/meet/neds/2022/11/image_readtop_2022_1027831_16686429625239568.jpg"},{"title":"휴마트컴퍼니, 투자용 기술신용평가(TCB) ‘TI-2’ 매우 우수 등급 획득","contents":"멘탈헬스케어 앱 ‘트로스트’를 운영하는 IT 기업 (주)휴마트컴퍼니(대표 김동현)는 NICE평가정보에서 실시한 투자용 기술신용평가에서 매우우수에 해당하는 TI-2등급을 획득했다고 밝혔다. TCB(Technology Credit..","link":"https://mirakle.mk.co.kr/view.php?sc=51800012&year=2022&no=1022900","retrieved":1668575540134,"image":"https://file.mk.co.kr/meet/neds/2022/11/image_readtop_2022_1022900_16685634615238019.jpg"},{"title":"브이플랫폼, 여성벤처 성장 챌린지 대상 수상","contents":"브랜드 엑셀러레이터 플랫폼 운용사인 ㈜브이플랫폼(대표 설혜진)이 지난 11일 한국여성벤처협회에서 주관한 ‘여성벤처 성장챌린지’ 창업 공모전 시상식에서 대상을 수상했다고 16일 밝혔다. 브이플랫폼은 중소벤..","link":"https://mirakle.mk.co.kr/view.php?sc=51800012&year=2022&no=1022707","retrieved":1668575540137,"image":"https://file.mk.co.kr/meet/neds/2022/11/image_readtop_2022_1022707_16685617225237952.jpg"},{"title":"센디, 수제 그릭요거트 제조판매사 ㈜스위트바이오에\n\n콜드체인 운송서비스 제공","contents":"센디, 자체 개발 배차 시스템과 자체 보유 전국 차량 네트워크 기반 화물운송 서비스 제공 식자재 운송, 완제품 ..","link":"https://mirakle.mk.co.kr/view.php?sc=51800012&year=2022&no=1022650","retrieved":1668575540138,"image":"https://file.mk.co.kr/meet/neds/2022/11/image_readtop_2022_1022650_16685609425237931.jpg"},{"title":"퓨처플레이, ‘삼성웰스토리 테크업플러스’ 참가 스타트업 모집","contents":"푸드테크, 물류/유통, ESG 등 시드, 시리즈 A 단계의 스타트업 발굴 및 육성, 투자 경쟁력과 사업성 평가를 통해 ..","link":"https://mirakle.mk.co.kr/view.php?sc=51800012&year=2022&no=1022633","retrieved":1668575540145,"image":"https://file.mk.co.kr/meet/neds/2022/11/image_readtop_2022_1022633_16685607615237918.jpg"},{"title":"인덴트코퍼레이션, 브이리뷰 영상 후기 기반\n\n‘자동화 마케팅 플랫폼(AMP)’ 공개","contents":"인덴트코퍼레이션, 영상 후기 기반 AI 자동화 마케팅 플랫폼 ‘앰프’ 새롭게 선보여 양질의 영상 리뷰 다량 생산..","link":"https://mirakle.mk.co.kr/view.php?sc=51800012&year=2022&no=1022601","retrieved":1668575540145,"image":"https://file.mk.co.kr/meet/neds/2022/11/image_readtop_2022_1022601_16685604625237910.jpg"}]}