{"title":"미라클 어헤드 ─ Think Big 뉴스종합 ─ Tech","url":"https://mirakle.mk.co.kr/list.php?sc=51800014","favicon":"https://mirakle.mk.co.kr/favicon.ico","elements":[{"title":"뉴 아이디, LG TV 에 31개 FAST 채널 론칭","contents":"콘텐츠미디어그룹 NEW(넥스트엔터테인먼트월드, 회장 김우택)의 첫 사내벤처 뉴 아이디(NEW ID, 대표 박준경)가 30일, LG 전자의 글로벌 콘텐츠 스트리밍 플랫폼 LG 채널(LG Channels) 한국에 드라마, 예능, 교양, ..","link":"https://mirakle.mk.co.kr/view.php?sc=51800014&year=2022&no=1083475","retrieved":1669867917922,"image":"https://file.mk.co.kr/meet/neds/2022/12/image_readtop_2022_1083475_16698567025258606.png"},{"title":"“클라우드는 이제 개발팀 뿐 아니라 재무팀도 알아야”","contents":"베스핀글로벌 옵스나우 개발 담당 박정호 상무 “시각화와 정확한 할당 통해 클라우드 지출 최적화” “AI로 사용..","link":"https://mirakle.mk.co.kr/view.php?sc=51800014&year=2022&no=1078665","retrieved":1669788796057,"image":"https://file.mk.co.kr/meet/neds/2022/11/image_readtop_2022_1078665_16697682615256883.jpg"},{"title":"플래티어, 2022 인사이트 리포트 ‘제 3호’ 발행","contents":"NFT(대체불가토큰) 주제.. 마케팅 효과 분석  디지털 플랫폼 솔루션 전문기업 플래..","link":"https://mirakle.mk.co.kr/view.php?sc=51800014&year=2022&no=1075072","retrieved":1669709476921,"image":"https://file.mk.co.kr/meet/neds/2022/11/image_readtop_2022_1075072_16696888225255559.png"},{"title":"트레저데이터, ‘인플레이션 시대’ 마케팅 조사 결과 공개","contents":"미국 소비자 2000명과 마케터 대상 조사 마케터 10명중 7명 “예산 삭감” “고객 데이터 최적화 부실로 38% 낭비..","link":"https://mirakle.mk.co.kr/view.php?sc=51800014&year=2022&no=1055381","retrieved":1669309677815,"image":"https://file.mk.co.kr/meet/neds/2022/11/image_readtop_2022_1055381_16691846425247862.jpg"},{"title":"플래티어, ‘디지털 마케팅 인사이트 2023’서 인사이트 발표","contents":"디지털 플랫폼 솔루션 전문기업 플래티어(대표 이상훈)가 22일 잠실 롯데호텔에서 열리는 ‘디지털 마케팅 인사이트 2023’에 참석해 퍼스트파티 데이터를 활용한 이커머스 고객 공략법을 소개했다고 22일 밝혔다. ..","link":"https://mirakle.mk.co.kr/view.php?sc=51800014&year=2022&no=1049346","retrieved":1669111759763,"image":"https://file.mk.co.kr/meet/neds/2022/11/image_readtop_2022_1049346_16690967425246490.png"},{"title":"엔터프라이즈블록체인-‘동남아 우버’ 그랩, 합작사 설립 나선다","contents":"재능마켓플래폼 구축 인도네시아에 공동구축  딥테크 기업 ‘엔터프라이즈블록체인..","link":"https://mirakle.mk.co.kr/view.php?sc=51800014&year=2022&no=1031971","retrieved":1668691680384,"image":"https://file.mk.co.kr/meet/neds/2022/11/image_readtop_2022_1031971_16686738025240773.png"},{"title":"플래티어, 3분기 매출 134억...2분기 연속 최대 매출 경신","contents":"매출 전년동기대비 10.2% 증가 순이익 114% 늘어난 22억원 디지털 플랫폼 솔루션 ..","link":"https://mirakle.mk.co.kr/view.php?sc=51800014&year=2022&no=1014731","retrieved":1668438756159,"image":"https://file.mk.co.kr/meet/neds/2022/11/image_readtop_2022_1014731_16684003215234806.png"},{"title":"\"저널리즘이 그 어느 때보다 중요하다\".. 언론인들이 함께 외친 이유","contents":"지금 전세계에서 언론의 자유가 위협받고 있다. 저널리즘이 그 어느 때보다 중요하다(Journalism Matters)  지난 9월 28일부터 30일까지 스페인 사라고사에서 열린 세계뉴스미디어총회(World News Media Congres..","link":"https://mirakle.mk.co.kr/view.php?sc=51800014&year=2022&no=924054","retrieved":1666150714876,"image":"https://file.mk.co.kr/meet/neds/2022/10/image_readtop_2022_924054_16661423385201601.jpg"},{"title":"커지는 한국 버추얼 시장.. 남성 버추얼 아이돌 CGV서 쇼케이스","contents":"이번달 29일 신인 아이돌 그룹이 서울의 CGV 영화관에서 신곡 발표 `쇼케이스`를 한다. 디지털 싱글 앨범과 두 가지 버전의 뮤직비디오를 최초 공개한다. 그런데 이 아이돌 그룹은  CGV 용산아이파크몰, 왕십리, ..","link":"https://mirakle.mk.co.kr/view.php?sc=51800014&year=2022&no=921017","retrieved":1666075955328,"image":"https://file.mk.co.kr/meet/neds/2022/10/image_readtop_2022_921017_16660686575200466.jpg"},{"title":"플래티어 그루비, 개인화 상품 추천 장치 특허 취득","contents":"디지털 플랫폼 솔루션 전문기업 ‘플래티어(대표이사 이상훈)’가 지난 9월 개인화 상품 추천과 관련하여 상품 추천 장치, 방법 및 기록 매체 특허 등록을 완료했다고 13일 밝혔다.  플래티어가 이번에 등록한 특..","link":"https://mirakle.mk.co.kr/view.php?sc=51800014&year=2022&no=906365","retrieved":1665699085391,"image":"https://file.mk.co.kr/meet/neds/2022/10/image_readtop_2022_906365_16656444075195643.jpg"}]}