{"title":"미라클 어헤드 ─ Think Big 뉴스종합 ─ 전체","url":"https://mirakle.mk.co.kr/list.php?sc=51800012","favicon":"https://mirakle.mk.co.kr/favicon.ico","elements":[{"title":"어반베이스, ‘스타일AI’ 출시..”개인별 맞춤형 인테리어 제안”","contents":"토털 리빙 플랫폼 기업 ㈜어반베이스(대표 하진우)가 인테리어 이미지를 자동 생성해주는 ‘스타일AI’ 베타버전 서비스를 출시했다고 13일 밝혔다. 스타일AI는 어반베이스가 자체 개발 및 제작한 최첨단 기술로, ..","link":"https://mirakle.mk.co.kr/view.php?sc=51800012&year=2023&no=531833","retrieved":1689215194336,"image":"https://file.mk.co.kr/meet/neds/2023/07/image_readtop_2023_531833_16892126415545275.png"},{"title":"의료기기 보증서 스타트업 서티라이프, 시드 투자 유치","contents":"디지털 의료 기기 보증서 서비스 운영 스타트업 서티라이프(CertiLife)가 치과의사 및 블록체인 업계로부터 시드 투자를 유치했다. 투자 금액은 비공개이다. 서티라이프는 블록체인 기술을 활용하여 의료 기기 보증..","link":"https://mirakle.mk.co.kr/view.php?sc=51800012&year=2023&no=531832","retrieved":1689215194338,"image":"https://file.mk.co.kr/meet/neds/2023/07/image_readtop_2023_531832_16892126415545274.png"},{"title":"초개인화 솔루션 옴니어스, ‘KAIT 고성능 컴퓨팅 연산 지원 사업’ 선정","contents":"초개인화 커머스 AI 기업 옴니어스(주)(대표 전재영)가 한국정보통신진흥협회(KAIT) 주관 ’2023년 고성능 컴퓨팅 연산 지원 사업‘에 선정됐다고 밝혔다. 국내 초거대 인공지능 활용확산 촉진 및 생태계 활성화 도..","link":"https://mirakle.mk.co.kr/view.php?sc=51800012&year=2023&no=531758","retrieved":1689215194340,"image":"https://file.mk.co.kr/meet/neds/2023/07/image_readtop_2023_531758_16892119825545246.png"},{"title":"버넥트, ‘2023 비대면 서비스 바우처’ 공급기업 선정","contents":"글로벌 XR(eXtended Reality, 확장현실) 테크 기업 버넥트(대표 하태진)가  ‘2023 비대면 서비스 바우처’ 공급기업으로 선정됐다고 13일 밝혔다. 중소벤처기업부가 주관하는 ‘비대면 서비스 바우처(K-voucher)’..","link":"https://mirakle.mk.co.kr/view.php?sc=51800012&year=2023&no=531669","retrieved":1689215194342,"image":"https://file.mk.co.kr/meet/neds/2023/07/image_readtop_2023_531669_16892110215545218.png"},{"title":"리디, 인기 웹소설 ‘만 개의 등을 너에게 바친다’ 드라마 공동개발","contents":"콘텐츠 플랫폼 기업 리디(대표 배기식)는 인기 웹소설 ‘만 개의 등을 너에게 바친다’의 드라마 공동개발에 나선다고 13일 밝혔다. 웹소설 ‘만 개의 등을 너에게 바친다’는 죽었던 남편 ‘백영’이 세자빈 ‘연..","link":"https://mirakle.mk.co.kr/view.php?sc=51800012&year=2023&no=531644","retrieved":1689215194345,"image":"https://file.mk.co.kr/meet/neds/2023/07/image_readtop_2023_531644_16892108425545208.jpg"},{"title":"당근마켓, ‘동네생활 가이드라인 2.0’ 발표","contents":"국내 대표 지역생활 커뮤니티 당근마켓(각자대표 김용현, 황도연)은 건강한 커뮤니티 문화와 서비스 환경을 조성하기 위해 기존 동네생활 가이드라인을 한층 강화한 ‘동네생활 가이드라인 2.0’을 공개했다고 13일..","link":"https://mirakle.mk.co.kr/view.php?sc=51800012&year=2023&no=531634","retrieved":1689215194347,"image":"https://file.mk.co.kr/meet/neds/2023/07/image_readtop_2023_531634_16892106615545196.jpg"},{"title":"미래 항공 모빌리티 점검 솔루션 개발 ‘위플로’, 프리시리즈A 투자 유치","contents":"미래 항공 모빌리티(AAM, Advanced Air Mobility) 점검 자동화 솔루션을 개발하는 위플로(대표 김의정)가 30억 원 규모 프리시리즈A 투자를 유치했다고 13일 밝혔다. 이번 투자는 키움투자자산운용, 기업은행, GS벤..","link":"https://mirakle.mk.co.kr/view.php?sc=51800012&year=2023&no=531570","retrieved":1689215194394,"image":"https://file.mk.co.kr/meet/neds/2023/07/image_readtop_2023_531570_16892100025545182.png"},{"title":"쿠콘, IBK기업은행과 손잡고 디지털 신시장 개척","contents":"비즈니스 데이터 플랫폼 기업 쿠콘이 IBK기업은행과 국내외 서비스형 뱅킹(Banking as a Service, 이하 BaaS) 시장 선점을 목표로 디지털금융 신시장 개척을 위해 업무 협약을 12일 체결했다. 협약식은  12일 서울 ..","link":"https://mirakle.mk.co.kr/view.php?sc=51800012&year=2023&no=529989","retrieved":1689149478161,"image":"https://file.mk.co.kr/meet/neds/2023/07/image_readtop_2023_529989_16891494625544445.jpg"},{"title":"그립 클라우드, 원클릭 기능 신규 출시","contents":"그립컴퍼니(대표 김한나)가 운영하는 라이브 커머스 SaaS 솔루션 그립  클라우드가 ‘원클릭 기능’을 신규 출시했다. 그립 클라우드는 기업이 자사 홈페이지 또는 앱에서 직접 라이브 커머스를 할 수 있게 만든 솔..","link":"https://mirakle.mk.co.kr/view.php?sc=51800012&year=2023&no=528291","retrieved":1689131922123,"image":"https://file.mk.co.kr/meet/neds/2023/07/image_readtop_2023_528291_16891281615543900.jpg"},{"title":"XL8, 미국 트랜스크립션 회사 ‘AHT’ 인수… AI 기술 정확도 향상","contents":"미디어 콘텐츠에 최적화된 인공지능 기계 번역 기술을 제공하는 미국 실리콘밸리 스타트업 엑스엘에이트 (XL8, 대표 정영훈)는 미국 정부에 속기, 트랜스크립션(전사) 및 번역 서비스를 제공하고 있는 American Hig..","link":"https://mirakle.mk.co.kr/view.php?sc=51800012&year=2023&no=528210","retrieved":1689131922126,"image":"https://file.mk.co.kr/meet/neds/2023/07/image_readtop_2023_528210_16891274415543865.png"}]}